gradio_iframe/__init__.py
gradio_iframe/iframe.py
gradio_iframe/iframe.pyi
gradio_iframe/templates/component/index.js
gradio_iframe/templates/component/style.css
gradio_iframe/templates/example/index.js
gradio_iframe/templates/example/style.css
gradio_iframe-0.0.10.dist-info/METADATA
gradio_iframe-0.0.10.dist-info/WHEEL
gradio_iframe-0.0.10.dist-info/RECORD
